sensoff/__init__.py
sensoff/__main__.py
sensoff/__version__.py
sensoff/sensoff.py
sensoff-1.2.dist-info/AUTHORS.md
sensoff-1.2.dist-info/LICENSE
sensoff-1.2.dist-info/METADATA
sensoff-1.2.dist-info/WHEEL
sensoff-1.2.dist-info/top_level.txt
sensoff-1.2.dist-info/zip-safe
sensoff-1.2.dist-info/RECORD
