Metadata-Version: 2.1
Name: sensoff
Version: 1.2
Summary: Corrects GPS transect coordinates to account for on-the-go sensor offsets
Home-page: https://github.com/usda-ars-ussl/sensoff
Author: Todd Skaggs
Author-email: todd.skaggs@usda.gov
License: Public Domain CC0
Platform: UNKNOWN
Classifier: Development Status :: 5 - Production/Stable
Classifier: Intended Audience :: Science/Research
Classifier: Topic :: Scientific/Engineering
Classifier: License :: CC0 1.0 Universal (CC0 1.0) Public Domain Dedication
Classifier: Natural Language :: English
Classifier: Programming Language :: Python :: 3
Requires-Python: >=3.7
